etc/intelmq/manager-apache.conf
intelmq_manager/__init__.py
intelmq_manager/build.py
intelmq_manager/manager-apache.conf
intelmq_manager/version.py
intelmq_manager/static/css/management.css
intelmq_manager/static/css/management.css.map
intelmq_manager/static/css/sb-admin-2.css
intelmq_manager/static/css/sb-admin-2.css.map
intelmq_manager/static/css/style.css
intelmq_manager/static/css/style.css.map
intelmq_manager/static/images/1140x319.gif
intelmq_manager/static/images/about.png
intelmq_manager/static/images/abouticon-20.png
intelmq_manager/static/images/abouticon-24.png
intelmq_manager/static/images/botnet.png
intelmq_manager/static/images/check.png
intelmq_manager/static/images/check.svg
intelmq_manager/static/images/config.png
intelmq_manager/static/images/logo.png
intelmq_manager/static/images/logo2.png
intelmq_manager/static/images/logo_no_margin_6.png
intelmq_manager/static/images/monitor.png
intelmq_manager/static/images/redrawicon-20.png
intelmq_manager/static/images/saveicon-128.png
intelmq_manager/static/images/saveicon-20.png
intelmq_manager/static/images/saveicon-24.png
intelmq_manager/static/images/trashicon-20.png
intelmq_manager/static/images/waiting.gif
intelmq_manager/static/js/about.js
intelmq_manager/static/js/check.js
intelmq_manager/static/js/config.js
intelmq_manager/static/js/configs.js
intelmq_manager/static/js/defaults.js
intelmq_manager/static/js/intelmq-manager.js
intelmq_manager/static/js/management.js
intelmq_manager/static/js/monitor.js
intelmq_manager/static/js/network-configuration.js
intelmq_manager/static/js/positions.js
intelmq_manager/static/js/runtime.js
intelmq_manager/static/js/sb-admin-2.js
intelmq_manager/static/js/static.js
intelmq_manager/static/less/management.less
intelmq_manager/static/less/sb-admin-2.less
intelmq_manager/static/less/style.less
intelmq_manager/static/plugins/jquery-3.5.1.js
intelmq_manager/static/plugins/jquery-3.5.1.min.js
intelmq_manager/static/plugins/jquery-3.5.1.min.map
intelmq_manager-3.2.0.dist-info/METADATA
intelmq_manager-3.2.0.dist-info/WHEEL
intelmq_manager-3.2.0.dist-info/entry_points.txt
intelmq_manager-3.2.0.dist-info/top_level.txt
intelmq_manager-3.2.0.dist-info/RECORD
